aliyunsdkcloudauth/__init__.py
aliyunsdkcloudauth/endpoint.py
aliyunsdkcloudauth/request/__init__.py
aliyunsdkcloudauth/request/v20190307/AIGCFaceVerifyRequest.py
aliyunsdkcloudauth/request/v20190307/CompareFaceVerifyRequest.py
aliyunsdkcloudauth/request/v20190307/CompareFacesRequest.py
aliyunsdkcloudauth/request/v20190307/ContrastFaceVerifyRequest.py
aliyunsdkcloudauth/request/v20190307/CreateAuthKeyRequest.py
aliyunsdkcloudauth/request/v20190307/CreateVerifySettingRequest.py
aliyunsdkcloudauth/request/v20190307/DescribeDeviceInfoRequest.py
aliyunsdkcloudauth/request/v20190307/DescribeFaceVerifyRequest.py
aliyunsdkcloudauth/request/v20190307/DescribeOssUploadTokenRequest.py
aliyunsdkcloudauth/request/v20190307/DescribePageFaceVerifyDataRequest.py
aliyunsdkcloudauth/request/v20190307/DescribeSmartStatisticsPageListRequest.py
aliyunsdkcloudauth/request/v20190307/DescribeVerifyResultRequest.py
aliyunsdkcloudauth/request/v20190307/DescribeVerifySDKRequest.py
aliyunsdkcloudauth/request/v20190307/DescribeVerifyTokenRequest.py
aliyunsdkcloudauth/request/v20190307/DetectFaceAttributesRequest.py
aliyunsdkcloudauth/request/v20190307/Id2MetaVerifyRequest.py
aliyunsdkcloudauth/request/v20190307/InitFaceVerifyRequest.py
aliyunsdkcloudauth/request/v20190307/LivenessFaceVerifyRequest.py
aliyunsdkcloudauth/request/v20190307/Mobile3MetaDetailVerifyRequest.py
aliyunsdkcloudauth/request/v20190307/Mobile3MetaSimpleVerifyRequest.py
aliyunsdkcloudauth/request/v20190307/ModifyDeviceInfoRequest.py
aliyunsdkcloudauth/request/v20190307/VerifyMaterialRequest.py
aliyunsdkcloudauth/request/v20190307/__init__.py
aliyun_python_sdk_cloudauth-2.0.35.dist-info/LICENSE
aliyun_python_sdk_cloudauth-2.0.35.dist-info/METADATA
aliyun_python_sdk_cloudauth-2.0.35.dist-info/WHEEL
aliyun_python_sdk_cloudauth-2.0.35.dist-info/top_level.txt
aliyun_python_sdk_cloudauth-2.0.35.dist-info/RECORD
